{
  "project_info": {
    "project_number": "402106819307",
    "firebase_url": "https://chilq-58176.firebaseio.com",
    "project_id": "chilq-58176",
    "storage_bucket": "chilq-58176.appspot.com"
  },
  "client": [
    {
      "client_info": {
        "mobilesdk_app_id": "1:402106819307:android:23a69cea2a25ef1f",
        "android_client_info": {
          "package_name": "com.example.zz.chilq"
        }
      },
      "oauth_client": [
        {
          "client_id": "402106819307-2f01a565dhjo5k9223pnqrjhcjlm0634.apps.googleusercontent.com",
          "client_type": 3
        }
      ],
      "api_key": [
        {
          "current_key": "AIzaSyAa5nMi6JPbA7cHcz1RDl_x0yoipYsxJVI"
        }
      ],
      "services": {
        "analytics_service": {
          "status": 1
        },
        "appinvite_service": {
          "status": 1,
          "other_platform_oauth_client": []
        },
        "ads_service": {
          "status": 2
        }
      }
    }
  ],
  "configuration_version": "1"
}